{
  "addresses": [
    {
      "_id": "62f8da4d46a736023ac3cdf2",
      "address": "821 Grant Avenue, Guthrie, Delaware, 1556",
      "latitude": -20.833608,
      "longitude": 46.56426,
      "city": "Noxen",
      "state": "Alabama"
    },
    {
      "_id": "62f8da4d5b2581ed8f8505e9",
      "address": "906 Williams Court, Cutter, Hawaii, 9364",
      "latitude": 42.30888,
      "longitude": -59.439168,
      "city": "Marienthal",
      "state": "Tennessee"
    },
    {
      "_id": "62f8da4df1212f1d999fd4f2",
      "address": "106 Euclid Avenue, Campo, Illinois, 9929",
      "latitude": 8.029599,
      "longitude": -19.828219,
      "city": "Roulette",
      "state": "West Virginia"
    },
    {
      "_id": "62f8da4d20129056b39fe17b",
      "address": "667 Varick Street, Eagleville, New York, 2962",
      "latitude": -75.435671,
      "longitude": -61.666216,
      "city": "Leyner",
      "state": "Arizona"
    },
    {
      "_id": "62f8da4d5037869fbbccad3e",
      "address": "291 Bradford Street, Clarktown, Northern Mariana Islands, 1274",
      "latitude": 64.238047,
      "longitude": -47.399972,
      "city": "Cetronia",
      "state": "Iowa"
    },
    {
      "_id": "62f8da4d9158409e857161e8",
      "address": "342 Vandalia Avenue, Johnsonburg, Georgia, 9987",
      "latitude": 61.137273,
      "longitude": -135.062563,
      "city": "Ada",
      "state": "Ohio"
    },
    {
      "_id": "62f8da4dce741dcf20922128",
      "address": "238 Berriman Street, Bordelonville, California, 7018",
      "latitude": -86.516443,
      "longitude": -56.936051,
      "city": "Convent",
      "state": "Louisiana"
    },
    {
      "_id": "62f8da4d2a7ae267d252711e",
      "address": "914 Village Road, Farmington, Connecticut, 9241",
      "latitude": 26.309095,
      "longitude": 6.028009,
      "city": "Lawrence",
      "state": "Massachusetts"
    },
    {
      "_id": "62f8da4d4820631a77998695",
      "address": "234 Locust Avenue, Bluffview, North Dakota, 5084",
      "latitude": -43.117393,
      "longitude": 84.600026,
      "city": "Brecon",
      "state": "New Jersey"
    },
    {
      "_id": "62f8da4d23bdfa1165cf9e1e",
      "address": "912 Aurelia Court, Disautel, Oregon, 9616",
      "latitude": -81.794628,
      "longitude": 96.580949,
      "city": "Rehrersburg",
      "state": "Oklahoma"
    },
    {
      "_id": "62f8da4dd4219975b8a12da1",
      "address": "827 Colonial Court, Advance, Federated States Of Micronesia, 9700",
      "latitude": -34.321988,
      "longitude": -82.874297,
      "city": "Blanco",
      "state": "Arkansas"
    },
    {
      "_id": "62f8da4d917f987d4626f148",
      "address": "224 Nolans Lane, Graniteville, Rhode Island, 6442",
      "latitude": -65.509187,
      "longitude": -86.569616,
      "city": "Darlington",
      "state": "Maryland"
    },
    {
      "_id": "62f8da4dd1649b2aa40f7ba4",
      "address": "643 Garden Street, Whipholt, Vermont, 8430",
      "latitude": 38.789827,
      "longitude": -144.104385,
      "city": "Sedley",
      "state": "North Carolina"
    },
    {
      "_id": "62f8da4da54433e9a0ccfc24",
      "address": "363 Clifford Place, Walland, Minnesota, 9512",
      "latitude": 59.804623,
      "longitude": 165.538294,
      "city": "Saranap",
      "state": "South Carolina"
    },
    {
      "_id": "62f8da4d0af8a0e41d4a1bbb",
      "address": "397 Menahan Street, Golconda, Florida, 9033",
      "latitude": -63.406208,
      "longitude": 120.73636,
      "city": "Glenshaw",
      "state": "New Mexico"
    },
    {
      "_id": "62f8da4d218f4a529e97178c",
      "address": "297 Adams Street, Chestnut, Maine, 3826",
      "latitude": -53.301407,
      "longitude": -104.816379,
      "city": "Calvary",
      "state": "Alaska"
    },
    {
      "_id": "62f8da4dea7c4a3d31b91327",
      "address": "543 Engert Avenue, Brandermill, Michigan, 777",
      "latitude": -69.498173,
      "longitude": 135.443742,
      "city": "Berlin",
      "state": "Virgin Islands"
    },
    {
      "_id": "62f8da4d4cf16110bcd8c83a",
      "address": "989 Caton Place, Lupton, Washington, 6900",
      "latitude": 28.955411,
      "longitude": -156.457155,
      "city": "Rockhill",
      "state": "Wisconsin"
    },
    {
      "_id": "62f8da4d18e13b4fce5eaebc",
      "address": "798 Keap Street, Osage, Missouri, 2182",
      "latitude": -42.280462,
      "longitude": 144.334841,
      "city": "Westboro",
      "state": "Virginia"
    },
    {
      "_id": "62f8da4de72c120c3eba47f0",
      "address": "211 Johnson Avenue, Manila, Kentucky, 3081",
      "latitude": 55.379368,
      "longitude": -34.921508,
      "city": "Stewartville",
      "state": "Indiana"
    },
    {
      "_id": "62f8da4dd49f8777f34ad0ab",
      "address": "103 Bath Avenue, Rosedale, Palau, 347",
      "latitude": -44.100296,
      "longitude": 170.314812,
      "city": "Lindisfarne",
      "state": "Nevada"
    }
  ]
}